LICENSE
MANIFEST.in
README.md
setup.py
defaultsettings/__init__.py
defaultsettings/main.py
defaultsettings.egg-info/PKG-INFO
defaultsettings.egg-info/SOURCES.txt
defaultsettings.egg-info/dependency_links.txt
defaultsettings.egg-info/pbr.json
defaultsettings.egg-info/top_level.txt