Metadata-Version: 1.0
Name: defaultsettings
Version: 0.0.3
Summary: Handle settings with default in python
Home-page: https://github.com/oskarnyqvists/defaultsettings
Author: oskarnyqvist
Author-email: oskarnyqvist@gmail.com
License: The MIT License (MIT)
